jac/__init__.py
jac/base.py
jac/compat.py
jac/config.py
jac/exceptions.py
jac/extension.py
jac/parser.py
jac/compressors/__init__.py
jac/compressors/coffee.py
jac/compressors/javascript.py
jac/compressors/less.py
jac/compressors/sass.py
jac/contrib/__init__.py
jac/contrib/flask.py
jac-0.17.2.dist-info/DESCRIPTION.rst
jac-0.17.2.dist-info/METADATA
jac-0.17.2.dist-info/RECORD
jac-0.17.2.dist-info/WHEEL
jac-0.17.2.dist-info/metadata.json
jac-0.17.2.dist-info/top_level.txt
